[
  {
    "parking_date": "26-11-2025",
    "status": "failed",
    "created_at": "24-11-2025",
    "last_attempt": "25-11-2025",
    "attempt_message": "Booking not successful on 25-11-2025. Result: failed"
  },
  {
    "parking_date": "27-11-2025",
    "status": "failed",
    "created_at": "24-11-2025",
    "last_attempt": "26-11-2025",
    "attempt_message": "Booking not successful on 26-11-2025. Result: failed"
  },
  {
    "parking_date": "03-12-2025",
    "status": "failed",
    "created_at": "01-12-2025",
    "last_attempt": "02-12-2025",
    "attempt_message": "Booking not successful on 02-12-2025. Result: failed"
  }
]